nonebot_plugin_nmcweather/__init__.py
nonebot_plugin_nmcweather/data_source.py
nonebot_plugin_nmcweather/qx.json
nonebot_plugin_nmcweather/weather.py
nonebot_plugin_nmcweather-0.1.3.dist-info/METADATA
nonebot_plugin_nmcweather-0.1.3.dist-info/WHEEL
nonebot_plugin_nmcweather-0.1.3.dist-info/RECORD
