Metadata-Version: 2.3
Name: nonebot-plugin-nmcweather
Version: 0.1.3
Summary: 基于NMC API的NoneBot2天气查询插件，支持城市天气查询和省份区县查询
License: MIT
Keywords: nonebot2,nonebot,plugin,weather,onebot.v11
Author: junzishendu_ln.@163.com
Requires-Python: >=3.10,<4.0
Classifier: License :: OSI Approved :: MIT License
Classifier: Programming Language :: Python :: 3
Classifier: Programming Language :: Python :: 3.10
Classifier: Programming Language :: Python :: 3.11
Classifier: Programming Language :: Python :: 3.12
Classifier: Programming Language :: Python :: 3.13
Requires-Dist: httpx (>=0.28.1,<=1.0.0)
Requires-Dist: nonebot-adapter-onebot (>=2.4.6,<3.0.0)
Requires-Dist: nonebot2 (>=2.4.2,<3.0.0)
Project-URL: Homepage, https://github.com/orchiddream/nonebot-plugin-nmcweather
Project-URL: Repository, https://github.com/orchiddream/nonebot-plugin-nmcweather
